az_ssh_wrapper.py
az_ssh_wrapper-1.0.3.post1.dist-info/METADATA
az_ssh_wrapper-1.0.3.post1.dist-info/WHEEL
az_ssh_wrapper-1.0.3.post1.dist-info/entry_points.txt
az_ssh_wrapper-1.0.3.post1.dist-info/licenses/LICENSE
az_ssh_wrapper-1.0.3.post1.dist-info/RECORD
