Metadata-Version: 2.4
Name: az-ssh-wrapper
Version: 1.0.3.post1
Summary: SSH Wrapper for Azure CLI's `az ssh` command
Project-URL: Repository, https://github.com/swsphn/az-ssh-wrapper
Project-URL: Bug Tracker, https://github.com/swsphn/az-ssh-wrapper/issues
Author-email: David Wales <david.wales@swsphn.com.au>
License: MIT License
License-File: LICENSE
Keywords: ansible,azure,ssh,wrapper
Requires-Python: >=3.9
